MANIFEST.in
README.rst
rpI2C.py
setup.cfg
setup.py
rpI2C.egg-info/PKG-INFO
rpI2C.egg-info/SOURCES.txt
rpI2C.egg-info/dependency_links.txt
rpI2C.egg-info/top_level.txt