Metadata-Version: 1.0
Name: rpI2C
Version: 1.0.1
Summary: Raspberry Pi I2C library. See https://github/com/DJSymBiotiX/rpI2C for more.
Home-page: https://github.com/DJSymBiotiX/rpI2C
Author: Fernando Chorney
Author-email: fchorney@djsbx.com
License: MIT
Keywords: raspberry,pi,i2c
Platform: UNKNOWN
